brownpaperbag/__init__.py
brownpaperbag/authent.py
brownpaperbag/bpbgate.py
brownpaperbag/brownpaperbag.py
brownpaperbag/cli.py
brownpaperbag-2.0.4.dist-info/LICENSE
brownpaperbag-2.0.4.dist-info/METADATA
brownpaperbag-2.0.4.dist-info/WHEEL
brownpaperbag-2.0.4.dist-info/entry_points.txt
brownpaperbag-2.0.4.dist-info/top_level.txt
brownpaperbag-2.0.4.dist-info/RECORD
