Metadata-Version: 2.1
Name: brownpaperbag
Version: 2.0.4
Summary: Python3 API for the Bticino Myhomeserver1 gateway
Home-page: https://github.com/bpaulin/brownpaperbag
Author: Bruno Paulin
Author-email: brunopaulin@bpaulin.net
License: MIT license
Keywords: brownpaperbag bticino legrand myhomeserver1
Platform: UNKNOWN
Classifier: Development Status :: 5 - Production/Stable
Classifier: Intended Audience :: Developers
Classifier: License :: OSI Approved :: MIT License
Classifier: Natural Language :: English
Classifier: Programming Language :: Python :: 3.8
Requires-Dist: Click (>=7.0)
